{
  "main": {
    "id": "7b7bbfdf2509ec5a",
    "type": "split",
    "children": [
      {
        "id": "1c05da9b30f56587",
        "type": "tabs",
        "children": [
          {
            "id": "2f9a825c22e15913",
            "type": "leaf",
            "pinned": true,
            "state": {
              "type": "markdown",
              "state": {
                "file": "source/模板/新建图表页面.md",
                "mode": "source",
                "source": true
              },
              "pinned": true,
              "icon": "lucide-file",
              "title": "新建图表页面"
            }
          },
          {
            "id": "fccd1622d8878153",
            "type": "leaf",
            "state": {
              "type": "markdown",
              "state": {
                "file": "source/模板/Blog_Post_Header.md",
                "mode": "source",
                "source": false
              },
              "icon": "lucide-file",
              "title": "Blog_Post_Header"
            }
          },
          {
            "id": "f40d80a9b83595d8",
            "type": "leaf",
            "state": {
              "type": "markdown",
              "state": {
                "file": "source/index.md",
                "mode": "source",
                "source": false
              },
              "icon": "lucide-file",
              "title": "index"
            }
          },
          {
            "id": "0a3b4eec2d279827",
            "type": "leaf",
            "state": {
              "type": "markdown",
              "state": {
                "file": "source/_posts/国内商品期货动态升贴水机制深度研究与非洲胶交割可行性分析报告.md",
                "mode": "source",
                "source": false
              },
              "icon": "lucide-file",
              "title": "国内商品期货动态升贴水机制深度研究与非洲胶交割可行性分析报告"
            }
          }
        ],
        "currentTab": 3
      }
    ],
    "direction": "vertical"
  },
  "left": {
    "id": "6b30a7d6f85d5e19",
    "type": "split",
    "children": [
      {
        "id": "7b2440850eb67555",
        "type": "tabs",
        "children": [
          {
            "id": "3aa2153d944ca84e",
            "type": "leaf",
            "state": {
              "type": "file-explorer",
              "state": {
                "sortOrder": "byModifiedTime",
                "autoReveal": false
              },
              "icon": "lucide-folder-closed",
              "title": "Files"
            }
          },
          {
            "id": "00a208851e7bb063",
            "type": "leaf",
            "state": {
              "type": "search",
              "state": {
                "query": "左翼",
                "matchingCase": false,
                "explainSearch": false,
                "collapseAll": false,
                "extraContext": false,
                "sortOrder": "alphabetical"
              },
              "icon": "lucide-search",
              "title": "Search"
            }
          },
          {
            "id": "a5f2656a00f09f6b",
            "type": "leaf",
            "state": {
              "type": "bookmarks",
              "state": {},
              "icon": "lucide-bookmark",
              "title": "Bookmarks"
            }
          }
        ]
      }
    ],
    "direction": "horizontal",
    "width": 300
  },
  "right": {
    "id": "0cc7f9a3f80c9078",
    "type": "split",
    "children": [
      {
        "id": "2b7c4bfe80e06c32",
        "type": "tabs",
        "children": [
          {
            "id": "2360852b5175df08",
            "type": "leaf",
            "state": {
              "type": "backlink",
              "state": {
                "file": "source/_posts/万事万物都可以概括为解决问题的能力.md",
                "collapseAll": false,
                "extraContext": false,
                "sortOrder": "alphabetical",
                "showSearch": false,
                "searchQuery": "",
                "backlinkCollapsed": false,
                "unlinkedCollapsed": true
              },
              "icon": "links-coming-in",
              "title": "Backlinks for 万事万物都可以概括为解决问题的能力"
            }
          },
          {
            "id": "7022862b9ace5060",
            "type": "leaf",
            "state": {
              "type": "outgoing-link",
              "state": {
                "file": "source/_posts/万事万物都可以概括为解决问题的能力.md",
                "linksCollapsed": false,
                "unlinkedCollapsed": true
              },
              "icon": "links-going-out",
              "title": "Outgoing links from 万事万物都可以概括为解决问题的能力"
            }
          },
          {
            "id": "673792888a118ccf",
            "type": "leaf",
            "state": {
              "type": "tag",
              "state": {
                "sortOrder": "frequency",
                "useHierarchy": true,
                "showSearch": false,
                "searchQuery": ""
              },
              "icon": "lucide-tags",
              "title": "Tags"
            }
          },
          {
            "id": "7c5d0630cc049aa6",
            "type": "leaf",
            "state": {
              "type": "all-properties",
              "state": {
                "sortOrder": "frequency",
                "showSearch": false,
                "searchQuery": ""
              },
              "icon": "lucide-archive",
              "title": "All properties"
            }
          },
          {
            "id": "0f576a349b9d01a6",
            "type": "leaf",
            "state": {
              "type": "outline",
              "state": {
                "file": "source/_posts/全球与中国合成橡胶产业链深度研究报告：供需重构、价格机制与市场演变 (2026版).md",
                "followCursor": false,
                "showSearch": false,
                "searchQuery": ""
              },
              "icon": "lucide-list",
              "title": "Outline of 全球与中国合成橡胶产业链深度研究报告：供需重构、价格机制与市场演变 (2026版)"
            }
          },
          {
            "id": "1d2d21bc3385ca1c",
            "type": "leaf",
            "state": {
              "type": "git-view",
              "state": {},
              "icon": "git-pull-request",
              "title": "Source Control"
            }
          }
        ],
        "currentTab": 5
      }
    ],
    "direction": "horizontal",
    "width": 300
  },
  "left-ribbon": {
    "hiddenItems": {
      "switcher:Open quick switcher": false,
      "graph:Open graph view": false,
      "canvas:Create new canvas": false,
      "daily-notes:Open today's daily note": false,
      "templates:Insert template": false,
      "command-palette:Open command palette": false,
      "bases:Create new base": false,
      "obsidian-git:Open Git source control": false,
      "obsidian-shellcommands:Shell commands: Custom variables": false,
      "templater-obsidian:Templater": false
    }
  },
  "active": "3aa2153d944ca84e",
  "lastOpenFiles": [
    "source/charts/国内商品期货动态升贴水机制深度研究与非洲胶交割可行性分析报告_20260115134834/index.html",
    "source/charts/国内商品期货动态升贴水机制深度研究与非洲胶交割可行性分析报告_20260115134834",
    "source/_posts/帝国崩塌：太子集团陈志被捕、引渡与跨国犯罪网络的覆灭.md",
    "source/_posts/全球与中国合成橡胶产业链深度研究报告：供需重构、价格机制与市场演变 (2026版).md",
    "source/_posts/《铁雨》影评：武戏精彩、文戏亦不逊色.md",
    "source/charts/重塑美索不达米亚2003年后伊拉克石油工业的外资参与地缘政治博弈与能源版图演变_20260114160924/index.html",
    "source/charts/重塑美索不达米亚2003年后伊拉克石油工业的外资参与地缘政治博弈与能源版图演变_20260114160924",
    "source/_posts/重塑美索不达米亚：2003年后伊拉克石油工业的外资参与、地缘政治博弈与能源版图演变.md",
    "source/charts/重塑美索不达米亚2003年后伊拉克石油工业的外资参与地缘政治博弈与能源版图演变_20260114155609/index.html",
    "source/charts/重塑美索不达米亚2003年后伊拉克石油工业的外资参与地缘政治博弈与能源版图演变_20260114155609",
    "source/charts/股指期货投研框架/index.html",
    "source/charts/股指期货投研框架",
    "source/charts/2026年PVC出口退税取消政策影响分析/index.html",
    "source/charts/2026年PVC出口退税取消政策影响分析",
    "source/charts/全球与中国合成橡胶产业链深度研究报告供需重构价格机制与市场演变 2026版_20260114084218/index.html",
    "source/_posts/穿越周期与重塑定价：2023-2025年中国权益市场策略复盘与分析师预测精准度深度考评报告.md",
    "node_modules/hexo-filter-mermaid-diagrams/img/header.png",
    "node_modules/hexo-filter-mermaid-diagrams/img/git.png",
    "node_modules/hexo-filter-mermaid-diagrams/img/gantt.png",
    "node_modules/hexo-filter-mermaid-diagrams/img/class.png",
    "node_modules/hexo-filter-mermaid-diagrams/README.md",
    "node_modules/deep-assign/readme.md",
    "node_modules/is-obj/readme.md",
    "source/模板/博客模板.md",
    "source/_posts/2026-01-09-futures-report.md",
    "source/模板/Blog_Post_Header.md",
    "source/_posts/“南矛行动”与马杜罗政权的覆灭：2026年美国军事干预行动的地缘政治、法理逻辑与经济影响深度研究报告.md",
    "source/_posts/2026年中国经济展望：跨越周期的结构性重塑与“十五五”规划下的动能转换.md",
    "source/模板/嵌入网站.md",
    "source/模板/新建图表页面.md",
    "source/_posts/极地霸权与生存空间：美国对格陵兰岛地缘战略诉求的综合评估报告.md",
    "source/_posts/国内商品期货动态升贴水机制深度研究与非洲胶交割可行性分析报告.md",
    "source/charts/极地霸权与生存空间：美国对格陵兰岛地缘战略诉求的综合评估报告/index.html.md",
    "source/_posts/2026年拉丁美洲地缘政治格局重塑：左翼政府的退潮、生存与转型深度研究报告.md",
    "source/_posts/宏观经济波动的多维图景：真实经济周期（RBC）理论与经典周期体系的综合研究.md",
    "source/index.md",
    "source/_posts/xlj.md",
    "source/_posts/2026-01-05-daily-futures.md",
    "source/_posts/2025-12-31-daily-summary.md",
    "source/_posts/2025-12-26-futures-comprehensive-report.md",
    "node_modules/hexo-theme-butterfly/source/img/friend_404.gif",
    "node_modules/hexo-theme-butterfly/source/img/error-page.png",
    "node_modules/hexo-theme-butterfly/source/img/butterfly-icon.png",
    "node_modules/hexo-theme-butterfly/source/img/404.jpg",
    "source/img/avatar.png",
    "source/img/index.png"
  ]
}